dep_appearances/__init__.py
dep_appearances/appearances_report.py
dep_appearances/cli.py
dep_appearances/dependency.py
dep_appearances/import_statement.py
dep_appearances-0.0.2.dist-info/LICENSE
dep_appearances-0.0.2.dist-info/METADATA
dep_appearances-0.0.2.dist-info/WHEEL
dep_appearances-0.0.2.dist-info/entry_points.txt
dep_appearances-0.0.2.dist-info/top_level.txt
dep_appearances-0.0.2.dist-info/RECORD
