Metadata-Version: 2.1
Name: dep-appearances
Version: 0.0.2
Summary: A simple tool to see where your dependencies are imported
Home-page: https://github.com/jdlubrano/dep-appearances
Author: Joel Lubrano
Author-email: joel.lubrano@gmail.com
License: UNKNOWN
Project-URL: Bug Tracker, https://github.com/jdlubrano/dep-appearances/issues
Platform: UNKNOWN
Classifier: Programming Language :: Python :: 3
Classifier: License :: OSI Approved :: MIT License
Classifier: Operating System :: OS Independent
Requires-Python: >=3.6
License-File: LICENSE
Requires-Dist: pipfile
